{
  "_comment": "Deploy targets + glass-box URLs. Templates: {{mesh.*}}, {{bonding.*}}, {{payment.*}} from p31-constants.json. Consolidated live sites + Workers: p31-live-fleet.json. After edits: npm run verify:ecosystem",
  "schema": "p31.ecosystem/1.0.0",
  "updated": "2026-04-28",
  "_deployNote": "Order matches docs/ECOSYSTEM-PRODUCTION-11.md §4: constants + pnpm, K₄ trio, geodesic, agent/orchestrator/love-ledger, Google bridge, satellite Workers, passkey, EPCP command-center, donate-api, wcd33, p31ca Pages last. unified-k4-cage/ omitted (same worker name as k4-cage). p31-pwa + sovereign-command-center are Cloudflare Pages (build + pages deploy). Each deployable uses steps[][] argv arrays (no shell — scripts/ecosystem-deploy.mjs). Holistic edge audit: npm run quantum:cloud",
  "glassProbes": [
    {
      "id": "k4-personal-api-health",
      "url": "{{mesh.k4PersonalWorkerUrl}}/api/health",
      "group": "mesh",
      "note": "Canonical k4-personal liveness"
    },
    {
      "id": "k4-personal-api-mesh",
      "url": "{{mesh.k4PersonalWorkerUrl}}/api/mesh",
      "group": "mesh",
      "note": "Personal mesh JSON"
    },
    {
      "id": "k4-cage-health",
      "url": "{{mesh.k4CageWorkerUrl}}/api/health",
      "group": "mesh",
      "note": "Cage worker"
    },
    {
      "id": "k4-hubs-health",
      "url": "{{mesh.k4HubsWorkerUrl}}/health",
      "group": "mesh",
      "note": "Hub fusion liveness"
    },
    {
      "id": "p31ca-passkey-register-begin",
      "url": "https://p31ca.org{{mesh.passkeyApiBasePath}}/register-begin",
      "method": "POST",
      "expectJsonKey": "challenge",
      "group": "mesh",
      "note": "WebAuthn register-begin; 200 + challenge when p31-passkey zone route is live"
    },
    {
      "id": "geodesic-room-worker",
      "url": "https://geodesic-room.trimtab-signal.workers.dev/",
      "group": "mesh",
      "note": "GeodesicRoom DO v0.2 — JSON { service, version, ok }; WS /api/geodesic/:id/ws; see docs/GEODESIC-GAME-ENGINE-INTEGRATION.md"
    },
    {
      "id": "agent-hub-health",
      "url": "{{mesh.agentHubWorkerUrl}}/api/health",
      "group": "mesh",
      "note": "Agent hub"
    },
    {
      "id": "orchestrator-status",
      "url": "{{mesh.orchestratorWorkerUrl}}/api/orchestrator/status",
      "group": "orchestrator",
      "note": "May return 401/403 without Access — still 'edge up'"
    },
    {
      "id": "command-center-health",
      "url": "https://command-center.trimtab-signal.workers.dev/api/health",
      "group": "command-center",
      "note": "EPCP liveness. If Cloudflare Access wraps this path without bypass, fetch may follow login HTML — prefer Access bypass for GET /api/health (EDGE-SECURITY); operator-shift-public carries JSON shape check"
    },
    {
      "id": "operator-shift-public",
      "url": "https://command-center.trimtab-signal.workers.dev/api/operator/shift",
      "group": "command-center",
      "note": "GET public operator shift (PII-free); POST requires Access + operator role",
      "expectJsonKey": "public"
    },
    {
      "id": "p31ca-hub-root",
      "url": "https://p31ca.org/",
      "group": "pages",
      "note": "Technical hub (HTML)"
    },
    {
      "id": "p31ca-passport-short",
      "url": "https://p31ca.org/passport",
      "group": "pages",
      "note": "301 → passport-generator.html; AGENTS canonical /passport"
    },
    {
      "id": "p31ca-agents-short",
      "url": "https://p31ca.org/agents",
      "group": "pages",
      "note": "301 → fleet-agents.html; Worker · bot · Cortex roster + probes + paste-ready curl/wrangler"
    },
    {
      "id": "p31ca-mesh-start-page",
      "url": "https://p31ca.org/mesh-start.html",
      "group": "pages",
      "note": "PAR personal landing (CWP-P31-PAR); repo: soup.html → andromeda/.../p31ca/public/mesh-start.html"
    },
    {
      "id": "p31ca-social-molecules-page",
      "url": "https://p31ca.org/social-molecules.html",
      "group": "pages",
      "note": "Social Molecules · C.A.R.S. hub operator shell (boot, load, edge ribbon); registry id social-molecules"
    },
    {
      "id": "p31ca-cars-shorturl",
      "url": "https://p31ca.org/cars",
      "group": "pages",
      "note": "301 → social-molecules.html (_redirects); short path for C.A.R.S. cockpit"
    },
    {
      "id": "p31ca-initial-build-page",
      "url": "https://p31ca.org/initial-build.html",
      "group": "pages",
      "note": "Initial Build CWP-P31-IB-2026-01; short /build; intake→tetra bake (phased WBS)"
    },
    {
      "id": "p31ca-build-shorturl",
      "url": "https://p31ca.org/build",
      "group": "pages",
      "note": "301/302 → initial-build.html (Cloudflare _redirects); client follows redirect in glass + browsers"
    },
    {
      "id": "p31ca-family-sovereign-pack",
      "url": "https://p31ca.org/family-pack",
      "group": "pages",
      "note": "Household delivery handoff; 301 → family-sovereign-pack.html; prose in docs/FAMILY-SOVEREIGN-PACK.md"
    },
    {
      "id": "p31ca-public-surface-json",
      "url": "https://p31ca.org/p31-public-surface.json",
      "group": "contracts",
      "note": "p31.publicSurface/1.0.0 — trust/legal index + machine endpoints"
    },
    {
      "id": "p31ca-fleet-entities-json",
      "url": "https://p31ca.org/p31-fleet-entities.json",
      "group": "contracts",
      "note": "p31.fleetEntities/1.0.0 — merged roster consumed by fleet-agents.html; npm run build:fleet-entities in p31ca prebuild",
      "expectJsonKey": "schema"
    },
    {
      "id": "p31ca-privacy-page",
      "url": "https://p31ca.org/privacy",
      "group": "pages",
      "note": "301 → privacy.html; generic public deliverable"
    },
    {
      "id": "p31ca-security-txt",
      "url": "https://p31ca.org/.well-known/security.txt",
      "group": "pages",
      "note": "RFC 9116 security.txt; mailto contact"
    },
    {
      "id": "bonding-soup",
      "url": "{{bonding.publicUrl}}/",
      "group": "pages",
      "note": "BONDING vertical"
    },
    {
      "id": "donate-api-health",
      "url": "{{payment.donateApiHealthUrl}}",
      "group": "monetary",
      "note": "Stripe checkout Worker liveness; CWP-P31-MAP-2026-01 as-built"
    },
    {
      "id": "donate-api-health-workers-dev",
      "url": "{{payment.donateApiWorkersDevUrl}}/health",
      "group": "monetary",
      "note": "Same Worker as donate-api-health; default workers.dev subdomain (DNS-independent check)"
    },
    {
      "id": "creator-economy-contract",
      "url": "https://p31ca.org/creator-economy.json",
      "group": "contracts",
      "note": "Public JSON contract (verify:economy in p31ca)"
    },
    {
      "id": "home-assistant-lan-optional",
      "url": "{{integrations.endpoints.homeAssistantLanBase}}",
      "group": "integrations",
      "note": "Set integrations.endpoints.homeAssistantLanBase in p31-constants (e.g. http://hass:8123). Omitted from CLI + /ops/ when empty. LAN-only; same network as HA.",
      "skipIfEmpty": true
    }
  ],
  "deployables": [
    {
      "id": "apply-constants",
      "cwd": ".",
      "description": "Regenerate hub/constants mirrors from p31-constants.json (no Cloudflare)",
      "steps": [["npm", "run", "apply:constants"]]
    },
    {
      "id": "04-software-pnpm-install",
      "cwd": "andromeda/04_SOFTWARE",
      "description": "Workspace deps for k4-personal filter + shared packages (no Cloudflare)",
      "steps": [["pnpm", "install"]]
    },
    {
      "id": "k4-personal-worker",
      "cwd": "andromeda/04_SOFTWARE",
      "description": "Personal K₄ Worker — deploy before k4-hubs (service bindings)",
      "steps": [["pnpm", "--filter", "k4-personal", "run", "deploy"]]
    },
    {
      "id": "k4-cage-worker",
      "cwd": "andromeda/04_SOFTWARE/k4-cage",
      "description": "k4-cage family mesh + topology DOs",
      "steps": [["npx", "wrangler", "deploy"]]
    },
    {
      "id": "k4-hubs-worker",
      "cwd": "andromeda/04_SOFTWARE/k4-hubs",
      "description": "k4-hubs fusion — PERSONAL_MESH_URL must match mesh.k4PersonalWorkerUrl",
      "steps": [["npx", "wrangler", "deploy"]]
    },
    {
      "id": "geodesic-room-worker",
      "cwd": "andromeda/04_SOFTWARE/geodesic-room",
      "description": "GeodesicRoom DO (WS + shared shapes)",
      "steps": [["npx", "wrangler", "deploy"]]
    },
    {
      "id": "p31-agent-hub-worker",
      "cwd": "andromeda/04_SOFTWARE/p31-agent-hub",
      "description": "p31-agent-hub — service binds to K₄ trio",
      "steps": [["npx", "wrangler", "deploy"]]
    },
    {
      "id": "p31-orchestrator-worker",
      "cwd": "andromeda/04_SOFTWARE/workers",
      "description": "mesh.orchestratorWorkerUrl",
      "steps": [["npx", "wrangler", "deploy", "--config", "wrangler-orchestrator.toml"]]
    },
    {
      "id": "p31-workers-love-ledger",
      "cwd": "andromeda/04_SOFTWARE/workers",
      "description": "p31-workers — LoveTransactionDO + default wrangler.toml (separate from orchestrator config)",
      "steps": [["npx", "wrangler", "deploy"]]
    },
    {
      "id": "p31-google-bridge-worker",
      "cwd": "andromeda/04_SOFTWARE/p31-google-bridge",
      "description": "Google OAuth bridge — production vars + GOOGLE_CLIENT_SECRET secret",
      "steps": [["npx", "wrangler", "deploy", "--env", "production"]]
    },
    {
      "id": "bonding-relay",
      "cwd": "andromeda/04_SOFTWARE/bonding",
      "description": "bonding-relay Worker",
      "steps": [["npx", "wrangler", "deploy"]]
    },
    {
      "id": "genesis-gate",
      "cwd": "andromeda/04_SOFTWARE/genesis-gate",
      "description": "genesis-gate Worker",
      "steps": [["npx", "wrangler", "deploy"]]
    },
    {
      "id": "kenosis-mesh",
      "cwd": "andromeda/04_SOFTWARE/kenosis-mesh",
      "description": "kenosis-mesh Worker",
      "steps": [["npx", "wrangler", "deploy"]]
    },
    {
      "id": "p31-cortex",
      "cwd": "andromeda/04_SOFTWARE/p31-cortex",
      "description": "p31-cortex Worker",
      "steps": [["npx", "wrangler", "deploy"]]
    },
    {
      "id": "p31-forge",
      "cwd": "andromeda/04_SOFTWARE/p31-forge",
      "description": "p31-forge Worker",
      "steps": [["npx", "wrangler", "deploy"]]
    },
    {
      "id": "p31-hearing-ops",
      "cwd": "andromeda/04_SOFTWARE/p31-hearing-ops",
      "description": "p31-hearing-ops — Vite → Cloudflare Pages (ops.p31ca.org project)",
      "steps": [["npm", "run", "deploy"]]
    },
    {
      "id": "p31-state",
      "cwd": "andromeda/04_SOFTWARE/p31-state",
      "description": "p31-state Worker",
      "steps": [["npx", "wrangler", "deploy"]]
    },
    {
      "id": "p31-quantum-edge",
      "cwd": "andromeda/04_SOFTWARE/packages/quantum-edge",
      "description": "p31-quantum-edge — confirm real KV/D1 ids in wrangler.toml (not placeholders)",
      "steps": [["npx", "wrangler", "deploy"]]
    },
    {
      "id": "p31-pwa-pages",
      "cwd": "andromeda/04_SOFTWARE/packages/node-zero/pwa",
      "description": "p31-pwa — Vite dist → Cloudflare Pages project p31-pwa",
      "steps": [["npm", "install"], ["npm", "run", "build"], ["npx", "wrangler", "pages", "deploy"]]
    },
    {
      "id": "sovereign-command-center-pages",
      "cwd": "andromeda/04_SOFTWARE/sovereign-command-center",
      "description": "Next.js → Pages project p31-command-center (wrangler may need @cloudflare/next-on-pages; pages_build_output_dir is .next today)",
      "steps": [["npm", "install"], ["npm", "run", "build"], ["npx", "wrangler", "pages", "deploy"]]
    },
    {
      "id": "spaceship-relay",
      "cwd": "andromeda/04_SOFTWARE/spaceship-earth",
      "description": "spaceship-relay Worker",
      "steps": [["npx", "wrangler", "deploy"]]
    },
    {
      "id": "p31-telemetry",
      "cwd": "andromeda/04_SOFTWARE/telemetry-worker",
      "description": "p31-telemetry Worker",
      "steps": [["npx", "wrangler", "deploy"]]
    },
    {
      "id": "p31-bouncer",
      "cwd": "andromeda/04_SOFTWARE/cloudflare-worker/bouncer",
      "description": "p31-bouncer Worker",
      "steps": [["npx", "wrangler", "deploy"]]
    },
    {
      "id": "p31-social-broadcast",
      "cwd": "andromeda/04_SOFTWARE/cloudflare-worker",
      "description": "p31-social-broadcast — runs npm run build via wrangler [build]",
      "steps": [["npx", "wrangler", "deploy"]]
    },
    {
      "id": "p31-social-worker",
      "cwd": "andromeda/04_SOFTWARE/cloudflare-worker/social-drop-automation",
      "description": "p31-social-worker (social-drop-automation)",
      "steps": [["npx", "wrangler", "deploy"]]
    },
    {
      "id": "p31-passkey-worker",
      "cwd": "andromeda/04_SOFTWARE/p31ca/workers/passkey",
      "description": "WebAuthn — zone route p31ca.org/api/passkey/*",
      "steps": [["npx", "wrangler", "deploy", "--env", "production"]]
    },
    {
      "id": "command-center-worker",
      "cwd": "andromeda/04_SOFTWARE/cloudflare-worker/command-center",
      "description": "EPCP command-center Worker (command-center.trimtab-signal.workers.dev)",
      "steps": [["npx", "wrangler", "deploy"]]
    },
    {
      "id": "donate-api",
      "cwd": "andromeda/04_SOFTWARE/donate-api",
      "description": "Stripe Checkout Worker — secrets per donate-api/DEPLOY.md",
      "steps": [["npx", "wrangler", "deploy"]]
    },
    {
      "id": "wcd33-archive",
      "cwd": "wcd33-global-archive",
      "description": "WCD-33 global archive Worker",
      "steps": [["npm", "run", "deploy"]]
    },
    {
      "id": "p31ca-pages",
      "cwd": "andromeda/04_SOFTWARE/p31ca",
      "description": "p31ca.org Astro hub — last so static bundle + _redirects match live Workers",
      "steps": [["npm", "run", "deploy"]]
    }
  ]
}
